{
  "gitSyncId": "66fe3a88af2b8e5a2a63fbe1_2a792c4b-c6ba-4fbc-90b6-a57a8d2ed295",
  "id": "Dashboard_Organic_vs_Paid_Traffic_Source",
  "pluginId": "mysql-plugin",
  "pluginType": "DB",
  "unpublishedAction": {
    "actionConfiguration": {
      "body": "SELECT \n    DATE_FORMAT(incident_date, '%Y-%m') AS month,\n    'Organic' AS source_type,\n    SUM(CAST(organic_search_traffic AS DECIMAL)) AS total\nFROM violations_sites_main\nGROUP BY month\nUNION ALL\nSELECT \n    DATE_FORMAT(incident_date, '%Y-%m') AS month,\n    'Paid' AS source_type,\n    SUM(CAST(paid_search_traffic AS DECIMAL)) AS total\nFROM violations_sites_main\nGROUP BY month\nORDER BY month, source_type;",
      "encodeParamsToggle": true,
      "paginationType": "NONE",
      "pluginSpecifiedTemplates": [
        {
          "value": true
        }
      ],
      "timeoutInMillisecond": 10000
    },
    "confirmBeforeExecute": false,
    "datasource": {
      "id": "ResearchDB",
      "isAutoGenerated": false,
      "name": "ResearchDB",
      "pluginId": "mysql-plugin"
    },
    "dynamicBindingPathList": [],
    "executeOnLoad": false,
    "name": "Organic_vs_Paid_Traffic_Source",
    "pageId": "Dashboard",
    "userSetOnLoad": false
  }
}