{
  "gitSyncId": "66fe3a88af2b8e5a2a63fbe1_70458922-16e9-45de-896b-cbc53f62e577",
  "id": "Rightsholder Approval_countRightHolder",
  "pluginId": "mysql-plugin",
  "pluginType": "DB",
  "unpublishedAction": {
    "actionConfiguration": {
      "body": "select count(*) as count from rightHolderProfile;",
      "encodeParamsToggle": true,
      "paginationType": "NONE",
      "pluginSpecifiedTemplates": [
        {
          "value": true
        }
      ],
      "timeoutInMillisecond": 10000
    },
    "confirmBeforeExecute": false,
    "datasource": {
      "id": "ResearchDB",
      "isAutoGenerated": false,
      "name": "ResearchDB",
      "pluginId": "mysql-plugin"
    },
    "dynamicBindingPathList": [],
    "executeOnLoad": true,
    "name": "countRightHolder",
    "pageId": "Rightsholder Approval",
    "userSetOnLoad": false
  }
}